ognajd/__init__.py
ognajd/admin/__init__.py
ognajd/admin/models/__init__.py
ognajd/admin/models/model.py
ognajd/apps/__init__.py
ognajd/apps/config.py
ognajd/middleware/__init__.py
ognajd/middleware/context.py
ognajd/migrations/0001_initial.py
ognajd/migrations/0002_alter_version_id.py
ognajd/migrations/0003_version_author_version_author_name_and_more.py
ognajd/migrations/0004_version_ognajd_vers_content_eebabe_idx.py
ognajd/migrations/__init__.py
ognajd/models/__init__.py
ognajd/models/meta.py
ognajd/models/version.py
ognajd/src/__init__.py
ognajd/src/exceptions.py
ognajd/tests/__init__.py
ognajd/views/__init__.py
ognajd/views/history.py
django_ognajd-0.2.8.dist-info/LICENSE
django_ognajd-0.2.8.dist-info/METADATA
django_ognajd-0.2.8.dist-info/WHEEL
django_ognajd-0.2.8.dist-info/top_level.txt
django_ognajd-0.2.8.dist-info/RECORD
