Metadata-Version: 2.1
Name: django-ognajd
Version: 0.2.8
Summary: Django app which handles ORM objects' versions.
Home-page: https://github.com/omelched/django-ognajd
Author: Denis Omelchenko
Author-email: omelched@gmail.com
Project-URL: Bug Tracker, https://github.com/omelched/django-ognajd/issues
Project-URL: Changelog, https://github.com/omelched/django-ognajd/releases
Classifier: Development Status :: 3 - Alpha
Classifier: Environment :: Web Environment
Classifier: Framework :: Django
Classifier: Framework :: Django :: 3.2
Classifier: Intended Audience :: Developers
Classifier: License :: OSI Approved :: GNU Affero General Public License v3
Classifier: License :: OSI Approved :: GNU Affero General Public License v3 or later (AGPLv3+)
Classifier: Operating System :: OS Independent
Classifier: Natural Language :: English
Classifier: Operating System :: OS Independent
Classifier: Programming Language :: Python
Classifier: Programming Language :: Python :: 3
Classifier: Programming Language :: Python :: 3.9
Classifier: Topic :: Database
Classifier: Topic :: Internet
Classifier: Topic :: Internet :: WWW/HTTP
Classifier: Topic :: Utilities
Requires-Python: >=3.8
License-File: LICENSE
Requires-Dist: django>=3.2.7
Requires-Dist: jsondiff>=1.3.0
